{"0":{"date":1436400000005,"option_code":"10000031","option_name":"50ETF\u8d2d2015\u5e749\u67082.20","amount":1462172.0,"pre_settle":0.522,"open":0.4507,"highest":0.7474,"lowest":0.44,"close":0.71,"settlement_price":0.6914},"1":{"date":1436400000005,"option_code":"10000032","option_name":"50ETF\u8d2d2015\u5e749\u67082.25","amount":529115.0,"pre_settle":0.479,"open":0.4199,"highest":0.711,"lowest":0.4199,"close":0.711,"settlement_price":0.6696},"2":{"date":1436400000005,"option_code":"10000033","option_name":"50ETF\u8d2d2015\u5e749\u67082.30","amount":367963.0,"pre_settle":0.4482,"open":0.3992,"highest":0.66,"lowest":0.3992,"close":0.5978,"settlement_price":0.6164},"3":{"date":1436400000005,"option_code":"10000034","option_name":"50ETF\u8d2d2015\u5e749\u67082.35","amount":302133.0,"pre_settle":0.4061,"open":0.364,"highest":0.611,"lowest":0.364,"close":0.5807,"settlement_price":0.5786},"4":{"date":1436400000005,"option_code":"10000035","option_name":"50ETF\u8d2d2015\u5e749\u67082.40","amount":463544.0,"pre_settle":0.3698,"open":0.3385,"highest":0.55,"lowest":0.3385,"close":0.55,"settlement_price":0.5422},"5":{"date":1436400000005,"option_code":"10000036","option_name":"50ETF\u6cbd2015\u5e749\u67082.20","amount":543527.0,"pre_settle":0.0879,"open":0.1,"highest":0.1,"lowest":0.0555,"close":0.0682,"settlement_price":0.067},"6":{"date":1436400000005,"option_code":"10000037","option_name":"50ETF\u6cbd2015\u5e749\u67082.25","amount":140358.0,"pre_settle":0.0961,"open":0.11,"highest":0.11,"lowest":0.0621,"close":0.0661,"settlement_price":0.0693},"7":{"date":1436400000005,"option_code":"10000038","option_name":"50ETF\u6cbd2015\u5e749\u67082.30","amount":322618.0,"pre_settle":0.12,"open":0.132,"highest":0.1327,"lowest":0.0701,"close":0.0799,"settlement_price":0.0817},"8":{"date":1436400000005,"option_code":"10000039","option_name":"50ETF\u6cbd2015\u5e749\u67082.35","amount":150235.0,"pre_settle":0.1323,"open":0.1525,"highest":0.1649,"lowest":0.0801,"close":0.088,"settlement_price":0.0911},"9":{"date":1436400000005,"option_code":"10000040","option_name":"50ETF\u6cbd2015\u5e749\u67082.40","amount":127751.0,"pre_settle":0.1534,"open":0.169,"highest":0.1768,"lowest":0.1028,"close":0.1028,"settlement_price":0.1037},"10":{"date":1436400000005,"option_code":"10000047","option_name":"50ETF\u8d2d2015\u5e749\u67082.45","amount":128078.0,"pre_settle":0.362,"open":0.3138,"highest":0.5298,"lowest":0.3138,"close":0.5298,"settlement_price":0.5091},"11":{"date":1436400000005,"option_code":"10000048","option_name":"50ETF\u6cbd2015\u5e749\u67082.45","amount":35257.0,"pre_settle":0.1734,"open":0.1894,"highest":0.1894,"lowest":0.11,"close":0.11,"settlement_price":0.1142},"12":{"date":1436400000005,"option_code":"10000055","option_name":"50ETF\u8d2d2015\u5e749\u67082.50","amount":171720.0,"pre_settle":0.3356,"open":0.2906,"highest":0.4515,"lowest":0.2906,"close":0.4515,"settlement_price":0.4687},"13":{"date":1436400000005,"option_code":"10000056","option_name":"50ETF\u6cbd2015\u5e749\u67082.50","amount":108575.0,"pre_settle":0.1997,"open":0.2264,"highest":0.2602,"lowest":0.1346,"close":0.1346,"settlement_price":0.1338},"14":{"date":1436400000005,"option_code":"10000063","option_name":"50ETF\u8d2d2015\u5e749\u67082.55","amount":167867.0,"pre_settle":0.3105,"open":0.2716,"highest":0.475,"lowest":0.2695,"close":0.4699,"settlement_price":0.4484},"15":{"date":1436400000005,"option_code":"10000064","option_name":"50ETF\u6cbd2015\u5e749\u67082.55","amount":44071.0,"pre_settle":0.2202,"open":0.2525,"highest":0.2525,"lowest":0.1318,"close":0.1472,"settlement_price":0.1514},"16":{"date":1436400000005,"option_code":"10000071","option_name":"50ETF\u8d2d2015\u5e749\u67082.60","amount":96386.0,"pre_settle":0.2866,"open":0.2509,"highest":0.43,"lowest":0.2509,"close":0.4201,"settlement_price":0.41},"17":{"date":1436400000005,"option_code":"10000072","option_name":"50ETF\u6cbd2015\u5e749\u67082.60","amount":234687.0,"pre_settle":0.248,"open":0.2511,"highest":0.28,"lowest":0.16,"close":0.16,"settlement_price":0.1683},"18":{"date":1436400000005,"option_code":"10000079","option_name":"50ETF\u8d2d2015\u5e749\u67082.65","amount":346127.0,"pre_settle":0.277,"open":0.232,"highest":0.4199,"lowest":0.23,"close":0.4199,"settlement_price":0.3938},"19":{"date":1436400000005,"option_code":"10000080","option_name":"50ETF\u6cbd2015\u5e749\u67082.65","amount":219113.0,"pre_settle":0.2591,"open":0.3093,"highest":0.3093,"lowest":0.1756,"close":0.1876,"settlement_price":0.1904},"20":{"date":1436400000005,"option_code":"10000087","option_name":"50ETF\u8d2d2015\u5e749\u67082.70","amount":78483.0,"pre_settle":0.2429,"open":0.2148,"highest":0.385,"lowest":0.2148,"close":0.385,"settlement_price":0.3632},"21":{"date":1436400000005,"option_code":"10000088","option_name":"50ETF\u6cbd2015\u5e749\u67082.70","amount":130257.0,"pre_settle":0.3261,"open":0.3398,"highest":0.36,"lowest":0.2,"close":0.2252,"settlement_price":0.2252},"22":{"date":1436400000005,"option_code":"10000095","option_name":"50ETF\u8d2d2015\u5e749\u67082.75","amount":245920.0,"pre_settle":0.2376,"open":0.1985,"highest":0.44,"lowest":0.1985,"close":0.3556,"settlement_price":0.3364},"23":{"date":1436400000005,"option_code":"10000096","option_name":"50ETF\u6cbd2015\u5e749\u67082.75","amount":85779.0,"pre_settle":0.33,"open":0.3717,"highest":0.3717,"lowest":0.1988,"close":0.2377,"settlement_price":0.2439},"24":{"date":1436400000005,"option_code":"10000103","option_name":"50ETF\u8d2d2015\u5e749\u67082.80","amount":441819.0,"pre_settle":0.2113,"open":0.1841,"highest":0.332,"lowest":0.1841,"close":0.2877,"settlement_price":0.2973},"25":{"date":1436400000005,"option_code":"10000104","option_name":"50ETF\u6cbd2015\u5e749\u67082.80","amount":151980.0,"pre_settle":0.4087,"open":0.4047,"highest":0.4486,"lowest":0.2548,"close":0.2548,"settlement_price":0.2597},"26":{"date":1436400000005,"option_code":"10000125","option_name":"50ETF\u8d2d2015\u5e749\u67082.85","amount":159199.0,"pre_settle":0.1918,"open":0.1704,"highest":0.3214,"lowest":0.1704,"close":0.2949,"settlement_price":0.2949},"27":{"date":1436400000005,"option_code":"10000126","option_name":"50ETF\u6cbd2015\u5e749\u67082.85","amount":260255.0,"pre_settle":0.4087,"open":0.4388,"highest":0.4388,"lowest":0.3076,"close":0.3076,"settlement_price":0.2956},"28":{"date":1436400000005,"option_code":"10000139","option_name":"50ETF\u8d2d2015\u5e749\u67082.90","amount":385007.0,"pre_settle":0.1714,"open":0.1605,"highest":0.29,"lowest":0.0971,"close":0.2615,"settlement_price":0.257},"29":{"date":1436400000005,"option_code":"10000140","option_name":"50ETF\u8d2d2015\u5e749\u67082.95","amount":167427.0,"pre_settle":0.1605,"open":0.1464,"highest":0.2687,"lowest":0.12,"close":0.2534,"settlement_price":0.2402},"30":{"date":1436400000005,"option_code":"10000141","option_name":"50ETF\u6cbd2015\u5e749\u67082.90","amount":181334.0,"pre_settle":0.4341,"open":0.474,"highest":0.474,"lowest":0.3084,"close":0.3084,"settlement_price":0.3119},"31":{"date":1436400000005,"option_code":"10000142","option_name":"50ETF\u6cbd2015\u5e749\u67082.95","amount":246829.0,"pre_settle":0.4613,"open":0.51,"highest":0.51,"lowest":0.3454,"close":0.3454,"settlement_price":0.346},"32":{"date":1436400000005,"option_code":"10000149","option_name":"50ETF\u8d2d2015\u5e749\u67083.00","amount":402679.0,"pre_settle":0.1557,"open":0.1374,"highest":0.2498,"lowest":0.1349,"close":0.2133,"settlement_price":0.2208},"33":{"date":1436400000005,"option_code":"10000150","option_name":"50ETF\u6cbd2015\u5e749\u67083.00","amount":112573.0,"pre_settle":0.531,"open":0.5468,"highest":0.5468,"lowest":0.399,"close":0.399,"settlement_price":0.399},"34":{"date":1436400000005,"option_code":"10000157","option_name":"50ETF\u8d2d2015\u5e749\u67083.10","amount":336853.0,"pre_settle":0.1399,"open":0.1212,"highest":0.216,"lowest":0.1149,"close":0.1919,"settlement_price":0.1922},"35":{"date":1436400000005,"option_code":"10000158","option_name":"50ETF\u6cbd2015\u5e749\u67083.10","amount":532460.0,"pre_settle":0.62,"open":0.6227,"highest":0.6227,"lowest":0.42,"close":0.42,"settlement_price":0.435},"36":{"date":1436400000005,"option_code":"10000165","option_name":"50ETF\u8d2d2015\u5e749\u67083.20","amount":257848.0,"pre_settle":0.1142,"open":0.098,"highest":0.1896,"lowest":0.033,"close":0.1636,"settlement_price":0.1636},"37":{"date":1436400000005,"option_code":"10000166","option_name":"50ETF\u6cbd2015\u5e749\u67083.20","amount":547939.0,"pre_settle":0.6513,"open":0.678,"highest":0.71,"lowest":0.505,"close":0.505,"settlement_price":0.5109},"38":{"date":1436400000005,"option_code":"10000173","option_name":"50ETF\u8d2d2015\u5e749\u67083.30","amount":165382.0,"pre_settle":0.0969,"open":0.087,"highest":0.1606,"lowest":0.0812,"close":0.1298,"settlement_price":0.1341},"39":{"date":1436400000005,"option_code":"10000174","option_name":"50ETF\u6cbd2015\u5e749\u67083.30","amount":741800.0000000001,"pre_settle":0.7437,"open":0.7814,"highest":0.7833,"lowest":0.62,"close":0.6309,"settlement_price":0.5956},"40":{"date":1436400000005,"option_code":"10000181","option_name":"50ETF\u8d2d2015\u5e749\u67083.40","amount":570276.0,"pre_settle":0.08,"open":0.0701,"highest":0.1319,"lowest":0.0701,"close":0.1159,"settlement_price":0.1113},"41":{"date":1436400000005,"option_code":"10000182","option_name":"50ETF\u6cbd2015\u5e749\u67083.40","amount":603595.0,"pre_settle":0.853,"open":0.8634,"highest":0.8634,"lowest":0.709,"close":0.709,"settlement_price":0.6701},"42":{"date":1436400000005,"option_code":"10000183","option_name":"50ETF\u8d2d2015\u5e7412\u67083.00","amount":224590.0,"pre_settle":0.2963,"open":0.2809,"highest":0.3973,"lowest":0.2809,"close":0.3481,"settlement_price":0.3592},"43":{"date":1436400000005,"option_code":"10000184","option_name":"50ETF\u8d2d2015\u5e7412\u67083.10","amount":196374.0,"pre_settle":0.2843,"open":0.2601,"highest":0.3532,"lowest":0.2601,"close":0.338,"settlement_price":0.3266},"44":{"date":1436400000005,"option_code":"10000185","option_name":"50ETF\u8d2d2015\u5e7412\u67083.20","amount":303024.0,"pre_settle":0.2564,"open":0.2393,"highest":0.36,"lowest":0.0023,"close":0.3035,"settlement_price":0.3035},"45":{"date":1436400000005,"option_code":"10000186","option_name":"50ETF\u8d2d2015\u5e7412\u67083.30","amount":236205.0,"pre_settle":0.2378,"open":0.2176,"highest":0.3288,"lowest":0.1505,"close":0.2774,"settlement_price":0.2774},"46":{"date":1436400000005,"option_code":"10000187","option_name":"50ETF\u8d2d2015\u5e7412\u67083.40","amount":142590.0,"pre_settle":0.2231,"open":0.1973,"highest":0.2723,"lowest":0.1821,"close":0.2723,"settlement_price":0.2549},"47":{"date":1436400000005,"option_code":"10000188","option_name":"50ETF\u6cbd2015\u5e7412\u67083.00","amount":11074.0,"pre_settle":0.5948,"open":0.6148,"highest":0.6148,"lowest":0.4926,"close":0.4926,"settlement_price":0.4926},"48":{"date":1436400000005,"option_code":"10000189","option_name":"50ETF\u6cbd2015\u5e7412\u67083.10","amount":78272.0,"pre_settle":0.655,"open":0.6872,"highest":0.6872,"lowest":0.554,"close":0.554,"settlement_price":0.5399},"49":{"date":1436400000005,"option_code":"10000190","option_name":"50ETF\u6cbd2015\u5e7412\u67083.20","amount":27570.0,"pre_settle":0.745,"open":0.7621,"highest":0.7621,"lowest":0.6413,"close":0.6413,"settlement_price":0.6151},"50":{"date":1436400000005,"option_code":"10000191","option_name":"50ETF\u6cbd2015\u5e7412\u67083.30","amount":117557.0,"pre_settle":0.8221,"open":0.8384,"highest":0.8384,"lowest":0.6684,"close":0.6684,"settlement_price":0.6746},"51":{"date":1436400000005,"option_code":"10000192","option_name":"50ETF\u6cbd2015\u5e7412\u67083.40","amount":17106.0,"pre_settle":0.8763,"open":0.916,"highest":0.916,"lowest":0.7946,"close":0.7946,"settlement_price":0.7946},"52":{"date":1436400000005,"option_code":"10000197","option_name":"50ETF\u8d2d2015\u5e749\u67083.50","amount":590756.0,"pre_settle":0.0699,"open":0.064,"highest":0.1107,"lowest":0.064,"close":0.0878,"settlement_price":0.089},"53":{"date":1436400000005,"option_code":"10000198","option_name":"50ETF\u6cbd2015\u5e749\u67083.50","amount":950061.0,"pre_settle":0.9558,"open":0.9467,"highest":0.9467,"lowest":0.6954,"close":0.7399,"settlement_price":0.7399},"54":{"date":1436400000005,"option_code":"10000199","option_name":"50ETF\u8d2d2015\u5e7412\u67083.50","amount":346134.0,"pre_settle":0.1831,"open":0.1736,"highest":0.28,"lowest":0.1524,"close":0.2188,"settlement_price":0.2188},"55":{"date":1436400000005,"option_code":"10000200","option_name":"50ETF\u6cbd2015\u5e7412\u67083.50","amount":58373.0,"pre_settle":0.9558,"open":0.9947,"highest":1.05,"lowest":0.8863,"close":0.8863,"settlement_price":0.8863},"56":{"date":1436400000005,"option_code":"10000201","option_name":"50ETF\u8d2d2015\u5e7412\u67082.95","amount":244501.0,"pre_settle":0.3219,"open":0.2961,"highest":0.4031,"lowest":0.2961,"close":0.3511,"settlement_price":0.364},"57":{"date":1436400000005,"option_code":"10000202","option_name":"50ETF\u6cbd2015\u5e7412\u67082.95","amount":10401.0,"pre_settle":0.5571,"open":0.5801,"highest":0.5801,"lowest":0.46,"close":0.46,"settlement_price":0.46},"58":{"date":1436400000005,"option_code":"10000203","option_name":"50ETF\u8d2d2015\u5e7412\u67082.90","amount":721685.0,"pre_settle":0.3219,"open":0.2945,"highest":0.4987,"lowest":0.25,"close":0.4229,"settlement_price":0.4017},"59":{"date":1436400000005,"option_code":"10000204","option_name":"50ETF\u6cbd2015\u5e7412\u67082.90","amount":190877.0,"pre_settle":0.5211,"open":0.5437,"highest":0.5587,"lowest":0.4306,"close":0.4306,"settlement_price":0.414},"60":{"date":1436400000005,"option_code":"10000205","option_name":"50ETF\u8d2d2015\u5e7412\u67082.85","amount":725238.0,"pre_settle":0.3379,"open":0.3092,"highest":0.4493,"lowest":0.2402,"close":0.4101,"settlement_price":0.4172},"61":{"date":1436400000005,"option_code":"10000206","option_name":"50ETF\u6cbd2015\u5e7412\u67082.85","amount":296589.0,"pre_settle":0.4626,"open":0.508,"highest":0.5429,"lowest":0.3702,"close":0.3702,"settlement_price":0.3839},"62":{"date":1436400000005,"option_code":"10000207","option_name":"50ETF\u8d2d2015\u5e747\u67083.10","amount":1631699.9999999998,"pre_settle":0.013,"open":0.021,"highest":0.0649,"lowest":0.013,"close":0.0478,"settlement_price":0.0478},"63":{"date":1436400000005,"option_code":"10000208","option_name":"50ETF\u8d2d2015\u5e747\u67083.20","amount":706173.0,"pre_settle":0.0072,"open":0.0075,"highest":0.0398,"lowest":0.0075,"close":0.0325,"settlement_price":0.0325},"64":{"date":1436400000005,"option_code":"10000209","option_name":"50ETF\u8d2d2015\u5e747\u67083.30","amount":464453.0000000001,"pre_settle":0.0072,"open":0.0075,"highest":0.0321,"lowest":0.007,"close":0.0159,"settlement_price":0.0159},"65":{"date":1436400000005,"option_code":"10000210","option_name":"50ETF\u8d2d2015\u5e747\u67083.40","amount":296707.0,"pre_settle":0.006,"open":0.004,"highest":0.0888,"lowest":0.004,"close":0.0094,"settlement_price":0.0094},"66":{"date":1436400000005,"option_code":"10000211","option_name":"50ETF\u8d2d2015\u5e747\u67083.50","amount":221127.0,"pre_settle":0.005,"open":0.004,"highest":0.012,"lowest":0.004,"close":0.0094,"settlement_price":0.0094},"67":{"date":1436400000005,"option_code":"10000212","option_name":"50ETF\u6cbd2015\u5e747\u67083.10","amount":3277605.0,"pre_settle":0.62,"open":0.6075,"highest":0.7094,"lowest":0.3596,"close":0.3651,"settlement_price":0.368},"68":{"date":1436400000005,"option_code":"10000213","option_name":"50ETF\u6cbd2015\u5e747\u67083.20","amount":3241117.0,"pre_settle":0.6513,"open":0.7,"highest":0.7373,"lowest":0.3941,"close":0.463,"settlement_price":0.463},"69":{"date":1436400000005,"option_code":"10000214","option_name":"50ETF\u6cbd2015\u5e747\u67083.30","amount":4004921.0,"pre_settle":0.7437,"open":0.7837,"highest":0.8136,"lowest":0.4833,"close":0.5301,"settlement_price":0.5301},"70":{"date":1436400000005,"option_code":"10000215","option_name":"50ETF\u6cbd2015\u5e747\u67083.40","amount":2514762.0,"pre_settle":0.853,"open":0.8888,"highest":0.8888,"lowest":0.5926,"close":0.6333,"settlement_price":0.6333},"71":{"date":1436400000005,"option_code":"10000216","option_name":"50ETF\u6cbd2015\u5e747\u67083.50","amount":4201032.0,"pre_settle":0.9558,"open":0.9798,"highest":1.0151,"lowest":0.6954,"close":0.73,"settlement_price":0.7284},"72":{"date":1436400000005,"option_code":"10000217","option_name":"50ETF\u8d2d2015\u5e747\u67082.95","amount":2200063.0,"pre_settle":0.022,"open":0.0256,"highest":0.0896,"lowest":0.025,"close":0.0785,"settlement_price":0.0785},"73":{"date":1436400000005,"option_code":"10000218","option_name":"50ETF\u8d2d2015\u5e747\u67083.00","amount":3756355.0,"pre_settle":0.02,"open":0.023,"highest":0.078,"lowest":0.023,"close":0.0698,"settlement_price":0.0698},"74":{"date":1436400000005,"option_code":"10000219","option_name":"50ETF\u6cbd2015\u5e747\u67082.95","amount":6802116.9999999991,"pre_settle":0.4423,"open":0.4621,"highest":0.4952,"lowest":0.187,"close":0.2437,"settlement_price":0.2437},"75":{"date":1436400000005,"option_code":"10000220","option_name":"50ETF\u6cbd2015\u5e747\u67083.00","amount":4772480.0,"pre_settle":0.531,"open":0.5599,"highest":0.5599,"lowest":0.2706,"close":0.2963,"settlement_price":0.2866},"76":{"date":1436400000005,"option_code":"10000223","option_name":"50ETF\u8d2d2015\u5e747\u67083.60","amount":211930.0,"pre_settle":0.0032,"open":0.0032,"highest":0.0099,"lowest":0.0031,"close":0.0099,"settlement_price":0.0094},"77":{"date":1436400000005,"option_code":"10000224","option_name":"50ETF\u6cbd2015\u5e747\u67083.60","amount":3951758.0,"pre_settle":1.0423,"open":1.0864,"highest":1.1246,"lowest":0.7819,"close":0.8587,"settlement_price":0.8361},"78":{"date":1436400000005,"option_code":"10000225","option_name":"50ETF\u8d2d2015\u5e749\u67083.60","amount":711668.0,"pre_settle":0.0599,"open":0.0548,"highest":0.082,"lowest":0.05,"close":0.0709,"settlement_price":0.0709},"79":{"date":1436400000005,"option_code":"10000226","option_name":"50ETF\u6cbd2015\u5e749\u67083.60","amount":1334723.0,"pre_settle":1.0423,"open":1.0311,"highest":1.1057,"lowest":0.7819,"close":0.8069,"settlement_price":0.8361},"80":{"date":1436400000005,"option_code":"10000227","option_name":"50ETF\u8d2d2015\u5e7412\u67083.60","amount":1019832.0,"pre_settle":0.1831,"open":0.1667,"highest":0.2145,"lowest":0.1368,"close":0.1914,"settlement_price":0.1891},"81":{"date":1436400000005,"option_code":"10000228","option_name":"50ETF\u6cbd2015\u5e7412\u67083.60","amount":282432.0,"pre_settle":1.0423,"open":1.0744,"highest":1.08,"lowest":0.8866,"close":0.9399,"settlement_price":0.9058},"82":{"date":1436400000005,"option_code":"10000229","option_name":"50ETF\u8d2d2015\u5e747\u67082.90","amount":3942796.0,"pre_settle":0.0308,"open":0.03,"highest":0.111,"lowest":0.03,"close":0.0935,"settlement_price":0.0935},"83":{"date":1436400000005,"option_code":"10000230","option_name":"50ETF\u6cbd2015\u5e747\u67082.90","amount":3755016.0,"pre_settle":0.4113,"open":0.4273,"highest":0.4581,"lowest":0.1554,"close":0.2203,"settlement_price":0.2203},"84":{"date":1436400000005,"option_code":"10000231","option_name":"50ETF\u8d2d2015\u5e747\u67082.75","amount":7756436.0,"pre_settle":0.046,"open":0.0517,"highest":0.1699,"lowest":0.0474,"close":0.1381,"settlement_price":0.1381},"85":{"date":1436400000005,"option_code":"10000232","option_name":"50ETF\u8d2d2015\u5e747\u67082.80","amount":6642535.0,"pre_settle":0.0347,"open":0.0479,"highest":0.15,"lowest":0.0409,"close":0.1154,"settlement_price":0.1154},"86":{"date":1436400000005,"option_code":"10000233","option_name":"50ETF\u8d2d2015\u5e747\u67082.85","amount":3578254.0,"pre_settle":0.031,"open":0.0322,"highest":0.1348,"lowest":0.0322,"close":0.1057,"settlement_price":0.1057},"87":{"date":1436400000005,"option_code":"10000234","option_name":"50ETF\u6cbd2015\u5e747\u67082.75","amount":9136687.0,"pre_settle":0.2867,"open":0.28,"highest":0.3248,"lowest":0.09,"close":0.1299,"settlement_price":0.1299},"88":{"date":1436400000005,"option_code":"10000235","option_name":"50ETF\u6cbd2015\u5e747\u67082.80","amount":5044921.0,"pre_settle":0.3058,"open":0.3367,"highest":0.3664,"lowest":0.111,"close":0.1489,"settlement_price":0.1489},"89":{"date":1436400000005,"option_code":"10000236","option_name":"50ETF\u6cbd2015\u5e747\u67082.85","amount":6044413.0,"pre_settle":0.3437,"open":0.3744,"highest":0.545,"lowest":0.1307,"close":0.178,"settlement_price":0.178},"90":{"date":1436400000005,"option_code":"10000237","option_name":"50ETF\u8d2d2015\u5e7412\u67082.75","amount":720164.0,"pre_settle":0.3645,"open":0.3242,"highest":0.5267,"lowest":0.2936,"close":0.4485,"settlement_price":0.4575},"91":{"date":1436400000005,"option_code":"10000238","option_name":"50ETF\u8d2d2015\u5e7412\u67082.80","amount":874672.0,"pre_settle":0.3489,"open":0.3231,"highest":0.4847,"lowest":0.2873,"close":0.4023,"settlement_price":0.4197},"92":{"date":1436400000005,"option_code":"10000239","option_name":"50ETF\u6cbd2015\u5e7412\u67082.75","amount":296656.0,"pre_settle":0.4254,"open":0.4401,"highest":0.4635,"lowest":0.3122,"close":0.3122,"settlement_price":0.3274},"93":{"date":1436400000005,"option_code":"10000240","option_name":"50ETF\u6cbd2015\u5e7412\u67082.80","amount":131757.0,"pre_settle":0.4523,"open":0.4737,"highest":0.4852,"lowest":0.373,"close":0.373,"settlement_price":0.358},"94":{"date":1436400000005,"option_code":"10000241","option_name":"50ETF\u8d2d2015\u5e748\u67082.90","amount":713746.0,"pre_settle":0.1303,"open":0.1154,"highest":0.2277,"lowest":0.1154,"close":0.196,"settlement_price":0.1907},"95":{"date":1436400000005,"option_code":"10000242","option_name":"50ETF\u8d2d2015\u5e748\u67082.95","amount":1144169.0,"pre_settle":0.1121,"open":0.1076,"highest":0.2,"lowest":0.056,"close":0.1699,"settlement_price":0.1699},"96":{"date":1436400000005,"option_code":"10000243","option_name":"50ETF\u8d2d2015\u5e748\u67083.00","amount":960390.0,"pre_settle":0.0966,"open":0.0927,"highest":0.1801,"lowest":0.0912,"close":0.1438,"settlement_price":0.1441},"97":{"date":1436400000005,"option_code":"10000244","option_name":"50ETF\u8d2d2015\u5e748\u67083.10","amount":1195294.0,"pre_settle":0.075,"open":0.0734,"highest":0.1303,"lowest":0.06,"close":0.1108,"settlement_price":0.1127},"98":{"date":1436400000005,"option_code":"10000245","option_name":"50ETF\u8d2d2015\u5e748\u67083.20","amount":1482979.0,"pre_settle":0.0585,"open":0.077,"highest":0.1075,"lowest":0.0375,"close":0.09,"settlement_price":0.0887},"99":{"date":1436400000005,"option_code":"10000246","option_name":"50ETF\u6cbd2015\u5e748\u67082.90","amount":509323.0,"pre_settle":0.4277,"open":0.4707,"highest":0.4707,"lowest":0.2475,"close":0.2848,"settlement_price":0.2879},"100":{"date":1436400000005,"option_code":"10000247","option_name":"50ETF\u6cbd2015\u5e748\u67082.95","amount":1129635.0,"pre_settle":0.4613,"open":0.5091,"highest":0.5091,"lowest":0.2758,"close":0.3212,"settlement_price":0.3142},"101":{"date":1436400000005,"option_code":"10000248","option_name":"50ETF\u6cbd2015\u5e748\u67083.00","amount":1251764.0,"pre_settle":0.531,"open":0.5484,"highest":0.5844,"lowest":0.3071,"close":0.3469,"settlement_price":0.3469},"102":{"date":1436400000005,"option_code":"10000249","option_name":"50ETF\u6cbd2015\u5e748\u67083.10","amount":944448.0,"pre_settle":0.62,"open":0.6295,"highest":0.6295,"lowest":0.3699,"close":0.4154,"settlement_price":0.4154},"103":{"date":1436400000005,"option_code":"10000250","option_name":"50ETF\u6cbd2015\u5e748\u67083.20","amount":683610.9999999999,"pre_settle":0.6513,"open":0.7133,"highest":0.7133,"lowest":0.4644,"close":0.4644,"settlement_price":0.4733},"104":{"date":1436400000005,"option_code":"10000251","option_name":"50ETF\u8d2d2015\u5e748\u67082.80","amount":1196705.0,"pre_settle":0.1563,"open":0.1423,"highest":0.2748,"lowest":0.1423,"close":0.2278,"settlement_price":0.2278},"105":{"date":1436400000005,"option_code":"10000252","option_name":"50ETF\u8d2d2015\u5e748\u67082.85","amount":1237342.0,"pre_settle":0.143,"open":0.1263,"highest":0.2542,"lowest":0.1263,"close":0.2045,"settlement_price":0.2077},"106":{"date":1436400000005,"option_code":"10000253","option_name":"50ETF\u6cbd2015\u5e748\u67082.80","amount":987821.0,"pre_settle":0.4087,"open":0.3972,"highest":0.3972,"lowest":0.15,"close":0.2403,"settlement_price":0.233},"107":{"date":1436400000005,"option_code":"10000254","option_name":"50ETF\u6cbd2015\u5e748\u67082.85","amount":689859.0,"pre_settle":0.4087,"open":0.4333,"highest":0.4333,"lowest":0.1483,"close":0.2496,"settlement_price":0.2496},"108":{"date":1436400000005,"option_code":"10000255","option_name":"50ETF\u8d2d2015\u5e747\u67082.60","amount":11882707.0,"pre_settle":0.093,"open":0.0779,"highest":0.2864,"lowest":0.0779,"close":0.2273,"settlement_price":0.2273},"109":{"date":1436400000005,"option_code":"10000256","option_name":"50ETF\u8d2d2015\u5e747\u67082.65","amount":9562440.0,"pre_settle":0.0818,"open":0.07,"highest":0.24,"lowest":0.07,"close":0.2084,"settlement_price":0.2084},"110":{"date":1436400000005,"option_code":"10000257","option_name":"50ETF\u8d2d2015\u5e747\u67082.70","amount":11152334.0,"pre_settle":0.0573,"open":0.08,"highest":0.2061,"lowest":0.06,"close":0.1619,"settlement_price":0.1619},"111":{"date":1436400000005,"option_code":"10000258","option_name":"50ETF\u6cbd2015\u5e747\u67082.60","amount":5204930.0000000009,"pre_settle":0.1761,"open":0.18,"highest":0.2151,"lowest":0.05,"close":0.0674,"settlement_price":0.0674},"112":{"date":1436400000005,"option_code":"10000259","option_name":"50ETF\u6cbd2015\u5e747\u67082.65","amount":4332393.0,"pre_settle":0.1922,"open":0.2123,"highest":0.2499,"lowest":0.0572,"close":0.0804,"settlement_price":0.0804},"113":{"date":1436400000005,"option_code":"10000260","option_name":"50ETF\u6cbd2015\u5e747\u67082.70","amount":6222370.0,"pre_settle":0.2593,"open":0.2432,"highest":0.2991,"lowest":0.0711,"close":0.0978,"settlement_price":0.0978},"114":{"date":1436400000005,"option_code":"10000261","option_name":"50ETF\u8d2d2015\u5e748\u67082.60","amount":1763966.0,"pre_settle":0.2548,"open":0.2025,"highest":0.3999,"lowest":0.2025,"close":0.345,"settlement_price":0.345},"115":{"date":1436400000005,"option_code":"10000262","option_name":"50ETF\u8d2d2015\u5e748\u67082.65","amount":1535567.0,"pre_settle":0.2317,"open":0.1851,"highest":0.376,"lowest":0.1851,"close":0.3135,"settlement_price":0.31},"116":{"date":1436400000005,"option_code":"10000263","option_name":"50ETF\u8d2d2015\u5e748\u67082.70","amount":1910971.0000000002,"pre_settle":0.2082,"open":0.1694,"highest":0.3833,"lowest":0.165,"close":0.283,"settlement_price":0.2831},"117":{"date":1436400000005,"option_code":"10000264","option_name":"50ETF\u8d2d2015\u5e748\u67082.75","amount":673058.0,"pre_settle":0.17,"open":0.1551,"highest":0.2996,"lowest":0.148,"close":0.2732,"settlement_price":0.2659},"118":{"date":1436400000005,"option_code":"10000265","option_name":"50ETF\u6cbd2015\u5e748\u67082.60","amount":1367781.0,"pre_settle":0.2359,"open":0.2669,"highest":0.2669,"lowest":0.12,"close":0.145,"settlement_price":0.1468},"119":{"date":1436400000005,"option_code":"10000266","option_name":"50ETF\u6cbd2015\u5e748\u67082.65","amount":656691.0,"pre_settle":0.2553,"open":0.297,"highest":0.3086,"lowest":0.15,"close":0.1603,"settlement_price":0.1609},"120":{"date":1436400000005,"option_code":"10000267","option_name":"50ETF\u6cbd2015\u5e748\u67082.70","amount":1569477.0,"pre_settle":0.3,"open":0.3289,"highest":0.3299,"lowest":0.1722,"close":0.1872,"settlement_price":0.1872},"121":{"date":1436400000005,"option_code":"10000268","option_name":"50ETF\u6cbd2015\u5e748\u67082.75","amount":678972.0,"pre_settle":0.3239,"open":0.3623,"highest":0.3818,"lowest":0.1872,"close":0.2145,"settlement_price":0.2122},"122":{"date":1436400000005,"option_code":"10000269","option_name":"50ETF\u8d2d2015\u5e7412\u67082.60","amount":316387.0,"pre_settle":0.53,"open":0.3951,"highest":0.5927,"lowest":0.3951,"close":0.5927,"settlement_price":0.5597},"123":{"date":1436400000005,"option_code":"10000270","option_name":"50ETF\u8d2d2015\u5e7412\u67082.65","amount":640990.0,"pre_settle":0.4036,"open":0.3289,"highest":0.5858,"lowest":0.3289,"close":0.5685,"settlement_price":0.5333},"124":{"date":1436400000005,"option_code":"10000271","option_name":"50ETF\u8d2d2015\u5e7412\u67082.70","amount":385884.0,"pre_settle":0.3888,"open":0.3371,"highest":0.5568,"lowest":0.3371,"close":0.4917,"settlement_price":0.4992},"125":{"date":1436400000005,"option_code":"10000272","option_name":"50ETF\u6cbd2015\u5e7412\u67082.60","amount":112268.0,"pre_settle":0.3251,"open":0.345,"highest":0.373,"lowest":0.2799,"close":0.2799,"settlement_price":0.2656},"126":{"date":1436400000005,"option_code":"10000273","option_name":"50ETF\u6cbd2015\u5e7412\u67082.65","amount":321041.0,"pre_settle":0.3549,"open":0.3786,"highest":0.4104,"lowest":0.3002,"close":0.302,"settlement_price":0.2871},"127":{"date":1436400000005,"option_code":"10000274","option_name":"50ETF\u6cbd2015\u5e7412\u67082.70","amount":239669.0,"pre_settle":0.3869,"open":0.4088,"highest":0.4125,"lowest":0.289,"close":0.289,"settlement_price":0.3017},"128":{"date":1436400000005,"option_code":"10000275","option_name":"50ETF\u8d2d2015\u5e747\u67082.55","amount":11399614.0,"pre_settle":0.1159,"open":0.106,"highest":0.325,"lowest":0.106,"close":0.2651,"settlement_price":0.2651},"129":{"date":1436400000005,"option_code":"10000276","option_name":"50ETF\u6cbd2015\u5e747\u67082.55","amount":5607689.0,"pre_settle":0.1761,"open":0.1726,"highest":0.1866,"lowest":0.0406,"close":0.0555,"settlement_price":0.0555},"130":{"date":1436400000005,"option_code":"10000277","option_name":"50ETF\u8d2d2015\u5e748\u67082.55","amount":870592.9999999999,"pre_settle":0.2614,"open":0.2201,"highest":0.4279,"lowest":0.2201,"close":0.38,"settlement_price":0.38},"131":{"date":1436400000005,"option_code":"10000278","option_name":"50ETF\u6cbd2015\u5e748\u67082.55","amount":709421.0,"pre_settle":0.2155,"open":0.2245,"highest":0.3,"lowest":0.11,"close":0.13,"settlement_price":0.1299},"132":{"date":1436400000005,"option_code":"10000279","option_name":"50ETF\u8d2d2015\u5e7412\u67082.55","amount":435019.0,"pre_settle":0.53,"open":0.3626,"highest":0.6335,"lowest":0.3626,"close":0.569,"settlement_price":0.5737},"133":{"date":1436400000005,"option_code":"10000280","option_name":"50ETF\u6cbd2015\u5e7412\u67082.55","amount":192451.0,"pre_settle":0.292,"open":0.3085,"highest":0.336,"lowest":0.24,"close":0.24,"settlement_price":0.2459},"134":{"date":1436400000005,"option_code":"10000281","option_name":"50ETF\u8d2d2015\u5e747\u67082.50","amount":14933381.0,"pre_settle":0.1262,"open":0.11,"highest":0.3866,"lowest":0.11,"close":0.3298,"settlement_price":0.3251},"135":{"date":1436400000005,"option_code":"10000282","option_name":"50ETF\u6cbd2015\u5e747\u67082.50","amount":7578782.0,"pre_settle":0.16,"open":0.1529,"highest":0.16,"lowest":0.035,"close":0.048,"settlement_price":0.048},"136":{"date":1436400000005,"option_code":"10000283","option_name":"50ETF\u8d2d2015\u5e748\u67082.50","amount":1481678.0,"pre_settle":0.3114,"open":0.2438,"highest":0.4818,"lowest":0.2438,"close":0.4264,"settlement_price":0.4264},"137":{"date":1436400000005,"option_code":"10000284","option_name":"50ETF\u6cbd2015\u5e748\u67082.50","amount":1228177.0,"pre_settle":0.1997,"open":0.2152,"highest":0.2152,"lowest":0.1001,"close":0.111,"settlement_price":0.111},"138":{"date":1436400000005,"option_code":"10000285","option_name":"50ETF\u8d2d2015\u5e7412\u67082.50","amount":372814.0,"pre_settle":0.53,"open":0.4052,"highest":0.6504,"lowest":0.4052,"close":0.6504,"settlement_price":0.6193},"139":{"date":1436400000005,"option_code":"10000286","option_name":"50ETF\u6cbd2015\u5e7412\u67082.50","amount":707029.0,"pre_settle":0.292,"open":0.2979,"highest":0.305,"lowest":0.228,"close":0.27,"settlement_price":0.2459}}